easypackage/__errors__.py
easypackage/__errors__.pyc
easypackage/__init__.py
easypackage/__init__.pyc
easypackage/release.py
easypackage/release.pyc
easypackage/root.py
easypackage/root.pyc
easypackage/syspath.py
easypackage/syspath.pyc
easypackage/tests/__init__.py
easypackage/tests/__main__.py
easypackage/tests/helper.py
easypackage/tests/test_release.py
easypackage/tests/test_root.py
easypackage/tests/test_syspath.py
easypackage/utils/__init__.py
easypackage/utils/banner.py
easypackage/utils/structures.py
easypackage/utils/legacy/__init__.py
easypackage/utils/legacy/dict.py
easypackage-0.1.8.dist-info/METADATA
easypackage-0.1.8.dist-info/RECORD
easypackage-0.1.8.dist-info/WHEEL
easypackage-0.1.8.dist-info/top_level.txt
easypackage-0.1.8.dist-info/zip-safe
