Metadata-Version: 2.1
Name: easypackage
Version: 0.1.8
Summary: Python packages - the simple way.
Home-page: https://github.com/grimen/python-easypackage
Author: Jonas Grimfelt
Author-email: grimen@gmail.com
License: MIT
Download-URL: https://github.com/grimen/python-easypackage
Project-URL: bugs, https://github.com/grimen/python-easypackage/issues
Project-URL: repository, https://github.com/grimen/python-easypackage
Keywords: python,package,module,easy,automatic,syspath,setup,release,root
Platform: UNKNOWN
Classifier: Topic :: Software Development :: Libraries
Classifier: Development Status :: 5 - Production/Stable
Classifier: Intended Audience :: Developers
Classifier: License :: OSI Approved :: MIT License
Classifier: Operating System :: POSIX
Classifier: Programming Language :: Python
Classifier: Programming Language :: Python :: 2
Classifier: Programming Language :: Python :: 2.7
Classifier: Programming Language :: Python :: 3
Classifier: Programming Language :: Python :: 3.6
Classifier: Programming Language :: Python :: Implementation :: CPython
Classifier: Programming Language :: Python :: Implementation :: PyPy
